{
  "category": "moving-image",
  "projects": [
    {
      "id": "0c315470-06d3-44c9-8c38-26b2aa0abf8a",
      "slug": "guinness-martian-landscape",
      "title": "Guinness Martian Landscape",
      "client": "Guinness",
      "type": "video",
      "thumbnail": "/images/moving-image/guinness-martian-landscape/thumbnail.jpg",
      "tags": [],
      "featured": false,
      "order": 1,
      "video": {
        "url": "/videos/guinness-martian-landscape.mp4",
        "poster": "/images/video-posters/guinness-martian-landscape.jpg",
        "width": 1280,
        "height": 720
      }
    },
    {
      "id": "1d15c91d-efaa-4f55-9f61-6830c8c5ac0c",
      "slug": "aloma-ice-cream",
      "title": "Aloma Ice cream",
      "type": "video",
      "thumbnail": "/images/moving-image/aloma-ice-cream/thumbnail.jpg",
      "tags": [],
      "featured": false,
      "order": 2,
      "video": {
        "url": "/videos/aloma-ice-cream.mp4",
        "poster": "/images/video-posters/aloma-ice-cream.jpg",
        "width": 386,
        "height": 290
      }
    },
    {
      "id": "37ffd612-788d-4eb2-a3a9-2dde4f5c1dc2",
      "slug": "aldi-christmas",
      "title": "Aldi Christmas",
      "type": "video",
      "thumbnail": "/images/moving-image/aldi-christmas/thumbnail.jpg",
      "tags": [],
      "featured": false,
      "order": 3,
      "video": {
        "url": "/videos/aldi-christmas.mp4",
        "poster": "/images/video-posters/aldi-christmas.jpg",
        "width": 1280,
        "height": 720
      }
    },
    {
      "id": "4b51fe94-aafd-46d0-88ec-769d36238a38",
      "slug": "findus-dawn-trawler-animation",
      "title": "Findus Dawn Trawler Animation",
      "type": "video",
      "thumbnail": "/images/moving-image/findus-dawn-trawler-animation/thumbnail.jpg",
      "tags": [],
      "featured": false,
      "order": 4,
      "video": {
        "url": "/videos/findus-dawn-trawler-animation.mp4",
        "poster": "/images/video-posters/findus-dawn-trawler-animation.jpg",
        "width": 1280,
        "height": 720
      }
    },
    {
      "id": "5883f88e-872d-4cf9-9318-97fa989582bf",
      "slug": "say-biscuit-one-more-time-jaffa-cakes",
      "title": "Say Biscuit One More Time - Jaffa Cakes",
      "type": "video",
      "thumbnail": "/images/moving-image/say-biscuit-one-more-time-jaffa-cakes/thumbnail.jpg",
      "tags": [],
      "featured": false,
      "order": 5,
      "video": {
        "url": "/videos/say-biscuit-one-more-time-jaffa-cakes.mp4",
        "poster": "/images/video-posters/say-biscuit-one-more-time-jaffa-cakes.jpg",
        "width": 480,
        "height": 854
      }
    },
    {
      "id": "6ed11c0b-dfba-41a8-b39b-e09bf436d1b7",
      "slug": "cadburys-twirl",
      "title": "Cadbury's Twirl",
      "type": "video",
      "thumbnail": "/images/moving-image/cadburys-twirl/thumbnail.jpg",
      "tags": [],
      "featured": false,
      "order": 6,
      "video": {
        "url": "/videos/cadburys-twirl.mp4",
        "poster": "/images/video-posters/cadburys-twirl.jpg",
        "width": 1280,
        "height": 720
      }
    },
    {
      "id": "7fe2ecbe-218f-4e14-8825-81f065e7eab1",
      "slug": "user-experience-onken-yoghurt",
      "title": "User Experience Onken Yoghurt",
      "type": "video",
      "thumbnail": "/images/moving-image/user-experience-onken-yoghurt/thumbnail.jpg",
      "tags": [],
      "featured": false,
      "order": 7,
      "video": {
        "url": "/videos/user-experience-onken-yoghurt.mp4",
        "poster": "/images/video-posters/user-experience-onken-yoghurt.jpg",
        "width": 1280,
        "height": 720
      }
    },
    {
      "id": "86c846f5-ae62-475f-b591-5716b9354fae",
      "slug": "moes-homewrecker",
      "title": "Moe's Homewrecker",
      "type": "video",
      "thumbnail": "/images/moving-image/moes-homewrecker/thumbnail.jpg",
      "tags": [],
      "featured": false,
      "order": 8,
      "video": {
        "url": "/videos/moes-homewrecker.mp4",
        "poster": "/images/video-posters/moes-homewrecker.jpg",
        "width": 960,
        "height": 540
      }
    },
    {
      "id": "884931f3-19cd-4df7-af4a-cf5b06b052a5",
      "slug": "cadburys-dairy-milk",
      "title": "Cadbury's Dairy Milk",
      "type": "video",
      "thumbnail": "/images/moving-image/cadburys-dairy-milk/thumbnail.jpg",
      "tags": [],
      "featured": false,
      "order": 9,
      "video": {
        "url": "/videos/cadburys-dairy-milk.mp4",
        "poster": "/images/video-posters/cadburys-dairy-milk.jpg",
        "width": 1152,
        "height": 720
      }
    },
    {
      "id": "95261e60-5e94-4e3e-8b63-8a2db121aaeb",
      "slug": "frozen-hortex",
      "title": "Frozen Hortex",
      "type": "video",
      "thumbnail": "/images/moving-image/frozen-hortex/thumbnail.jpg",
      "tags": [],
      "featured": false,
      "order": 10,
      "video": {
        "url": "/videos/frozen-hortex.mp4",
        "poster": "/images/video-posters/frozen-hortex.jpg",
        "width": 720,
        "height": 576
      }
    },
    {
      "id": "97f2f652-f517-48fc-82cf-dc9160617a03",
      "slug": "edward-beale-a-perspective",
      "title": "Edward Beale, A perspective",
      "type": "video",
      "thumbnail": "/images/moving-image/edward-beale-a-perspective/thumbnail.jpg",
      "tags": [],
      "featured": false,
      "order": 11,
      "video": {
        "url": "/videos/edward-beale-a-perspective.mp4",
        "poster": "/images/video-posters/edward-beale-a-perspective.jpg",
        "width": 320,
        "height": 240
      }
    },
    {
      "id": "a44fe54a-7c06-4a06-bf75-94dc90db6eec",
      "slug": "castello-cheese-pop-up",
      "title": "Castello Cheese Pop Up",
      "type": "video",
      "thumbnail": "/images/moving-image/castello-cheese-pop-up/thumbnail.jpg",
      "tags": [],
      "featured": false,
      "order": 12,
      "video": {
        "url": "/videos/castello-cheese-pop-up.mp4",
        "poster": "/images/video-posters/castello-cheese-pop-up.jpg",
        "width": 1280,
        "height": 720
      }
    },
    {
      "id": "d6bb7d6d-bafd-439b-a70a-af291cc650c6",
      "slug": "busy-day-film",
      "title": "Busy Day Film",
      "type": "video",
      "thumbnail": "/images/moving-image/busy-day-film/thumbnail.jpg",
      "tags": [],
      "featured": false,
      "order": 13,
      "video": {
        "url": "/videos/busy-day-film.mp4",
        "poster": "/images/video-posters/busy-day-film.jpg",
        "width": 1024,
        "height": 576
      }
    },
    {
      "id": "dbce1094-8f1c-4e5f-96aa-f5bfa7f22cf1",
      "slug": "cadburys-marvelous-mix",
      "title": "Cadbury's Marvelous Mix",
      "type": "video",
      "thumbnail": "/images/moving-image/cadburys-marvelous-mix/thumbnail.jpg",
      "tags": [],
      "featured": false,
      "order": 14,
      "video": {
        "url": "/videos/cadburys-marvelous-mix.mp4",
        "poster": "/images/video-posters/cadburys-marvelous-mix.jpg",
        "width": 606,
        "height": 1080
      }
    },
    {
      "id": "dc238244-1837-4467-8df3-9c95a915ce95",
      "slug": "kelloggs-special-k",
      "title": "Kellogg's Special K",
      "client": "Kellogg's",
      "type": "video",
      "thumbnail": "/images/moving-image/kelloggs-special-k/thumbnail.jpg",
      "tags": [],
      "featured": false,
      "order": 15,
      "video": {
        "url": "/videos/kelloggs-special-k.mp4",
        "poster": "/images/video-posters/kelloggs-special-k.jpg",
        "width": 720,
        "height": 576
      }
    }
  ]
}